LICENSE
MANIFEST.in
README.rst
requirements.txt
setup.py
example/__init__.py
example/manage.py
example/settings.py
example/urls.py
example/apps/__init__.py
example/apps/app1/__init__.py
example/apps/app1/management/__init__.py
example/apps/app1/management/appCommands/__init__.py
example/apps/app1/management/appCommands/prep.py
example/apps/app2/__init__.py
example/apps/app2/management/__init__.py
example/apps/app2/management/appCommands/__init__.py
example/apps/app2/management/appCommands/prep.py
geocamUtil/Builder.py
geocamUtil/BuilderTest.py
geocamUtil/FileUtil.py
geocamUtil/Installer.py
geocamUtil/InstallerTest.py
geocamUtil/JsonRpc2Validation.py
geocamUtil/KmlUtil.py
geocamUtil/KmlUtilTest.py
geocamUtil/MimeMultipartFormData.py
geocamUtil/MultiSettings.py
geocamUtil/MultiSettingsTest.py
geocamUtil/TimeUtil.py
geocamUtil/TimeUtilTest.py
geocamUtil/Xmp.py
geocamUtil/__init__.py
geocamUtil/anyjson.py
geocamUtil/anyjsonTest.py
geocamUtil/auth.py
geocamUtil/dateparse.py
geocamUtil/defaultSettings.py
geocamUtil/geo.py
geocamUtil/geomath.py
geocamUtil/geomathTest.py
geocamUtil/gpx.py
geocamUtil/minifyJs.py
geocamUtil/tempfiles.py
geocamUtil/tests.py
geocamUtil/timezone.py
geocamUtil/tzinfo.py
geocamUtil/wsflashpolicy.py
geocamUtil.egg-info/PKG-INFO
geocamUtil.egg-info/SOURCES.txt
geocamUtil.egg-info/dependency_links.txt
geocamUtil.egg-info/requires.txt
geocamUtil.egg-info/top_level.txt
geocamUtil/bin/__init__.py
geocamUtil/bin/runjsl.py
geocamUtil/bin/runpep8.py
geocamUtil/bin/runpylint.py
geocamUtil/context_processors/AuthUrlsContextProcessor.py
geocamUtil/context_processors/__init__.py
geocamUtil/forms/UuidField.py
geocamUtil/forms/__init__.py
geocamUtil/icons/__init__.py
geocamUtil/icons/halo.py
geocamUtil/icons/rotate.py
geocamUtil/icons/rotateTest.py
geocamUtil/icons/svg.py
geocamUtil/icons/svgTest.py
geocamUtil/management/__init__.py
geocamUtil/management/commandUtil.py
geocamUtil/management/commandsTest.py
geocamUtil/management/commands/__init__.py
geocamUtil/management/commands/bootstrap.py
geocamUtil/management/commands/collectbinaries.py
geocamUtil/management/commands/collectmedia.py
geocamUtil/management/commands/lint.py
