Metadata-Version: 1.0
Name: geocamUtil
Version: 0.1
Summary: geocamUtil -- Utilities used by Django apps in the GeoCam Share app collection.
Home-page: http://github.com/geocam/geocamUtilWeb
Author: Trey Smith
Author-email: trey.smith@nasa.gov
License: UNKNOWN
Platform: UNKNOWN
Classifier: License :: OSI Approved
Classifier: Framework :: Django
